{
  "timestamp": "2026-02-02T21:30:23.258Z",
  "duration": 10335,
  "mode": "full",
  "phases": [
    {
      "name": "users",
      "startTime": "2026-02-02T21:30:23.261Z",
      "endTime": "2026-02-02T21:30:23.422Z",
      "duration": 161,
      "status": "success",
      "itemsProcessed": 4,
      "itemsSkipped": 0,
      "itemsInserted": 4,
      "itemsUpdated": 0,
      "warnings": []
    },
    {
      "name": "authors",
      "startTime": "2026-02-02T21:30:23.433Z",
      "endTime": "2026-02-02T21:30:23.451Z",
      "duration": 18,
      "status": "success",
      "itemsProcessed": 25,
      "itemsSkipped": 0,
      "itemsInserted": 25,
      "itemsUpdated": 0,
      "warnings": []
    },
    {
      "name": "artists",
      "startTime": "2026-02-02T21:30:23.451Z",
      "endTime": "2026-02-02T21:30:23.463Z",
      "duration": 12,
      "status": "success",
      "itemsProcessed": 22,
      "itemsSkipped": 0,
      "itemsInserted": 22,
      "itemsUpdated": 0,
      "warnings": []
    },
    {
      "name": "genres",
      "startTime": "2026-02-02T21:30:23.464Z",
      "endTime": "2026-02-02T21:30:23.479Z",
      "duration": 15,
      "status": "success",
      "itemsProcessed": 36,
      "itemsSkipped": 0,
      "itemsInserted": 36,
      "itemsUpdated": 0,
      "warnings": []
    },
    {
      "name": "types",
      "startTime": "2026-02-02T21:30:23.480Z",
      "endTime": "2026-02-02T21:30:23.487Z",
      "duration": 7,
      "status": "success",
      "itemsProcessed": 3,
      "itemsSkipped": 0,
      "itemsInserted": 3,
      "itemsUpdated": 0,
      "warnings": []
    },
    {
      "name": "comics",
      "startTime": "2026-02-02T21:30:23.546Z",
      "endTime": "2026-02-02T21:30:33.590Z",
      "duration": 10044,
      "status": "success",
      "itemsProcessed": 627,
      "itemsSkipped": 157,
      "itemsInserted": 132,
      "itemsUpdated": 0,
      "warnings": []
    },
    {
      "name": "chapters",
      "startTime": "2026-02-02T21:30:33.591Z",
      "endTime": "2026-02-02T21:30:33.591Z",
      "duration": 0,
      "status": "success",
      "itemsProcessed": 5814,
      "itemsSkipped": 0,
      "itemsInserted": 2369,
      "itemsUpdated": 0,
      "warnings": []
    }
  ],
  "summary": {
    "totalItems": 6531,
    "totalInserted": 2591,
    "totalUpdated": 0,
    "totalSkipped": 157,
    "totalErrors": 0,
    "totalWarnings": 0
  },
  "errors": []
}
